{
  "applets": [{
    "lastAccessTime": "2026-05-03T14:45:05.388487Z",
    "firstAccessTime": "2026-05-03T14:33:41.428037Z",
    "source": {
      "sourceType": "SPANNER",
      "spanner": {
        "id": "0879489a-eb7b-4525-b3a0-bc5b0f67cd74"
      }
    },
    "name": "Roam \u0026 Ride",
    "description": "A high-conversion hotel booking and transportation platform with bundled deals and AI-powered travel concierge.",
    "runtimeType": 1
  }, {
    "lastAccessTime": "2026-05-03T14:32:43.123871Z",
    "firstAccessTime": "2026-05-03T14:26:59.150270Z",
    "source": {
      "sourceType": "SPANNER",
      "spanner": {
        "id": "48e96742-64e1-4c77-a2d5-d4a5b62fb754"
      }
    },
    "name": "StayGo",
    "description": "Premium hotel booking and transportation platform with bundled deals and real-time availability.",
    "runtimeType": 1
  }, {
    "lastAccessTime": "2026-05-03T14:32:28.679623Z",
    "firstAccessTime": "2026-05-03T14:32:28.679623Z",
    "source": {
      "sourceType": "SPANNER",
      "spanner": {
        "id": "b527b634-acc7-4080-92d4-4af58c6a2039"
      }
    },
    "name": "Untitled",
    "description": "Generated by Gemini."
  }]
}